LICENSE
README.rst
precise_bbcode/__init__.py
precise_bbcode/admin.py
precise_bbcode/apps.py
precise_bbcode/bbcode/__init__.py
precise_bbcode/bbcode/defaults/__init__.py
precise_bbcode/bbcode/defaults/placeholder.py
precise_bbcode/bbcode/defaults/tag.py
precise_bbcode/bbcode/exceptions.py
precise_bbcode/bbcode/parser.py
precise_bbcode/bbcode/placeholder.py
precise_bbcode/bbcode/regexes.py
precise_bbcode/bbcode/tag.py
precise_bbcode/conf/__init__.py
precise_bbcode/conf/settings.py
precise_bbcode/core/__init__.py
precise_bbcode/core/compat.py
precise_bbcode/core/loading.py
precise_bbcode/core/utils.py
precise_bbcode/fields.py
precise_bbcode/jinja2tags.py
precise_bbcode/locale/fr/LC_MESSAGES/django.mo
precise_bbcode/locale/fr/LC_MESSAGES/django.po
precise_bbcode/migrations/0001_initial.py
precise_bbcode/migrations/__init__.py
precise_bbcode/models.py
precise_bbcode/placeholder_pool.py
precise_bbcode/shortcuts.py
precise_bbcode/tag_pool.py
precise_bbcode/templatetags/__init__.py
precise_bbcode/templatetags/bbcode_tags.py
precise_bbcode/test.py
django_precise_bbcode-1.2.15.dist-info/LICENSE
django_precise_bbcode-1.2.15.dist-info/WHEEL
django_precise_bbcode-1.2.15.dist-info/METADATA
django_precise_bbcode-1.2.15.dist-info/RECORD
