Metadata-Version: 2.1
Name: django-precise-bbcode
Version: 1.2.15
Summary: A django BBCode integration..
Home-page: https://github.com/ellmetha/django-precise-bbcode
License: BSD-3-Clause
Keywords: django,bbdode,html
Author: Morgan Aubert
Author-email: me@morganaubert.name
Requires-Python: >=3.6,<4.0
Classifier: Development Status :: 4 - Beta
Classifier: Environment :: Web Environment
Classifier: Framework :: Django
Classifier: Intended Audience :: Developers
Classifier: License :: OSI Approved :: BSD License
Classifier: Natural Language :: English
Classifier: Programming Language :: Python
Classifier: Programming Language :: Python :: 3
Classifier: Programming Language :: Python :: 3.10
Classifier: Programming Language :: Python :: 3.6
Classifier: Programming Language :: Python :: 3.7
Classifier: Programming Language :: Python :: 3.8
Classifier: Programming Language :: Python :: 3.9
Requires-Dist: django (>=3.2)
Requires-Dist: pillow (>=2.2.1)
Project-URL: Repository, https://github.com/ellmetha/django-precise-bbcode
